llama_index/llms/google_genai/__init__.py
llama_index/llms/google_genai/base.py
llama_index/llms/google_genai/py.typed
llama_index/llms/google_genai/utils.py
llama_index_llms_google_genai-0.8.5.dist-info/METADATA
llama_index_llms_google_genai-0.8.5.dist-info/WHEEL
llama_index_llms_google_genai-0.8.5.dist-info/RECORD
