Metadata-Version: 2.4
Name: llama-index-llms-google-genai
Version: 0.8.5
Summary: llama-index llms google genai integration
Author-email: Your Name <you@example.com>
License-Expression: MIT
Requires-Python: <4.0,>=3.10
Requires-Dist: google-genai<2,>=1.52.0
Requires-Dist: llama-index-core<0.15,>=0.14.5
Requires-Dist: pillow>=10.2.0
